{
  "meta": {
    "component": "blocks/layout/hero/Hero012",
    "section": "a-propos/manifeste/hero012"
  },
  "data": {
    "overtitle": "LE MANIFESTE DE NILE",
    "title": "On ne fera pas l'industrie du futur avec les méthodes du siècle passé.",
    "subtitle": "La croissance industrielle a changé. Et vous ? Vous avez investi dans l'innovation produit, automatisé vos chaînes, imaginé l'usine du futur. Pourtant, votre manière de vendre est restée coincée quelque part dans les années 2000. Si nous n'avons pas de recette miracle, nous avons une méthode pour accompagner votre transformation.",
    "scrollAnchor": "#next-section"
  }
}